backmap/__init__.py
backmap/__main__.py
backmap/_version.py
backmap/backmap.py
backmap/cli.py
backmap/local_colormaps.py
backmap/utils.py
backmap-1.1.0.dist-info/licenses/AUTHORS.rst
backmap-1.1.0.dist-info/licenses/LICENSE
backmap-1.1.0.dist-info/METADATA
backmap-1.1.0.dist-info/WHEEL
backmap-1.1.0.dist-info/entry_points.txt
backmap-1.1.0.dist-info/top_level.txt
backmap-1.1.0.dist-info/RECORD
