Metadata-Version: 2.4
Name: backmap
Version: 1.1.0
Summary: Shows protein backbone structures in compact graphical form using Ramachandran numbers
Author-email: Ranjan Mannige <ranjanmannige@gmail.com>
Maintainer-email: Ranjan Mannige <ranjanmannige@gmail.com>
Project-URL: Homepage, https://github.com/ranjanmannige/backmap
Project-URL: Documentation, https://ranjanmannige.github.io/backmap/
Project-URL: Repository, https://github.com/ranjanmannige/backmap
Project-URL: Issues, https://github.com/ranjanmannige/backmap/issues
Classifier: Development Status :: 5 - Production/Stable
Classifier: Intended Audience :: Science/Research
Classifier: License :: OSI Approved :: MIT License
Classifier: Programming Language :: Python :: 3
Classifier: Programming Language :: Python :: 3 :: Only
Classifier: Programming Language :: Python :: 3.8
Classifier: Programming Language :: Python :: 3.9
Classifier: Programming Language :: Python :: 3.10
Classifier: Programming Language :: Python :: 3.11
Classifier: Programming Language :: Python :: 3.12
Classifier: Topic :: Scientific/Engineering :: Bio-Informatics
Requires-Python: >=3.8
License-File: LICENSE
License-File: AUTHORS.rst
Requires-Dist: matplotlib
Requires-Dist: pandas
Requires-Dist: typer
Requires-Dist: setuptools_scm
Provides-Extra: test
Requires-Dist: coverage; extra == "test"
Requires-Dist: pytest; extra == "test"
Requires-Dist: ruff; extra == "test"
Requires-Dist: ty; extra == "test"
Requires-Dist: ipdb; extra == "test"
Dynamic: license-file
